{"1":{"id":1,"level":1,"title":"two-sum","language":["javascript"],"generated":true},"2":{"id":2,"level":2,"title":"add-two-numbers","language":["javascript"],"generated":true},"7":{"id":7,"level":1,"title":"reverse-integer","language":["javascript"],"generated":true},"15":{"id":15,"level":2,"title":"3sum","language":["javascript"],"generated":true},"20":{"id":20,"level":1,"title":"valid-parentheses","language":["javascript"],"generated":true},"21":{"id":21,"level":1,"title":"merge-two-sorted-lists","language":["javascript"],"generated":true},"26":{"id":26,"level":1,"title":"remove-duplicates-from-sorted-array","language":["javascript"],"generated":true},"27":{"id":27,"level":1,"title":"remove-element","language":["javascript"],"generated":true},"49":{"id":49,"level":2,"title":"group-anagrams","language":["javascript"],"generated":true},"64":{"id":64,"level":2,"title":"minimum-path-sum","language":["javascript"],"generated":true},"70":{"id":70,"level":1,"title":"climbing-stairs","language":["javascript"],"generated":true},"71":{"id":71,"level":2,"title":"simplify-path","language":["javascript"],"generated":true},"75":{"id":75,"level":2,"title":"sort-colors","language":["javascript"],"generated":true},"80":{"id":80,"level":2,"title":"remove-duplicates-from-sorted-array-ii","language":["javascript"],"generated":true},"82":{"id":82,"level":2,"title":"remove-duplicates-from-sorted-list-ii","language":["javascript"],"generated":true},"83":{"id":83,"level":1,"title":"remove-duplicates-from-sorted-list","language":["javascript"],"generated":true},"86":{"id":86,"level":2,"title":"partition-list","language":["javascript"],"generated":true},"88":{"id":88,"level":1,"title":"merge-sorted-array","language":["javascript"],"generated":true},"92":{"id":92,"level":2,"title":"reverse-linked-list-ii","language":["javascript"],"generated":true},"94":{"id":94,"level":2,"title":"binary-tree-inorder-traversal","language":["javascript"],"generated":true},"100":{"id":100,"level":1,"title":"same-tree","language":["javascript"],"generated":true},"101":{"id":101,"level":1,"title":"symmetric-tree","language":["javascript"],"generated":true},"102":{"id":102,"level":2,"title":"binary-tree-level-order-traversal","language":["javascript"],"generated":true},"103":{"id":103,"level":2,"title":"binary-tree-zigzag-level-order-traversal","language":["javascript"],"generated":true},"104":{"id":104,"level":1,"title":"maximum-depth-of-binary-tree","language":["javascript"],"generated":true},"107":{"id":107,"level":1,"title":"binary-tree-level-order-traversal-ii","language":["javascript"],"generated":true},"110":{"id":110,"level":1,"title":"balanced-binary-tree","language":["javascript"],"generated":true},"111":{"id":111,"level":1,"title":"minimum-depth-of-binary-tree","language":["javascript"],"generated":true},"120":{"id":120,"level":2,"title":"triangle","language":["javascript"],"generated":true},"125":{"id":125,"level":1,"title":"valid-palindrome","language":["javascript"],"generated":true},"144":{"id":144,"level":2,"title":"binary-tree-preorder-traversal","language":["javascript"],"generated":true},"145":{"id":145,"level":3,"title":"binary-tree-postorder-traversal","language":["javascript"],"generated":true},"150":{"id":150,"level":2,"title":"evaluate-reverse-polish-notation","language":["javascript"],"generated":true},"167":{"id":167,"level":1,"title":"two-sum-ii-input-array-is-sorted","language":["javascript"],"generated":true},"199":{"id":199,"level":2,"title":"binary-tree-right-side-view","language":["javascript"],"generated":true},"202":{"id":202,"level":1,"title":"happy-number","language":["javascript"],"generated":true},"203":{"id":203,"level":1,"title":"remove-linked-list-elements","language":["javascript"],"generated":true},"206":{"id":206,"level":1,"title":"reverse-linked-list","language":["javascript"],"generated":true},"209":{"id":209,"level":2,"title":"minimum-size-subarray-sum","language":["javascript"],"generated":true},"222":{"id":222,"level":2,"title":"count-complete-tree-nodes","language":["javascript"],"generated":true},"226":{"id":226,"level":1,"title":"invert-binary-tree","language":["javascript"],"generated":true},"242":{"id":242,"level":1,"title":"valid-anagram","language":["javascript"],"generated":true},"279":{"id":279,"level":2,"title":"perfect-squares","language":["javascript"],"generated":true},"283":{"id":283,"level":1,"title":"move-zeroes","language":["javascript"],"generated":true},"290":{"id":290,"level":1,"title":"word-pattern","language":["javascript"],"generated":true},"328":{"id":328,"level":2,"title":"odd-even-linked-list","language":["javascript"],"generated":true},"341":{"id":341,"level":2,"title":"flatten-nested-list-iterator","language":["javascript"],"generated":true},"343":{"id":343,"level":2,"title":"integer-break","language":["javascript"],"generated":true},"344":{"id":344,"level":1,"title":"reverse-string","language":["javascript"],"generated":true},"345":{"id":345,"level":1,"title":"reverse-vowels-of-a-string","language":["javascript"],"generated":true},"347":{"id":347,"level":2,"title":"top-k-frequent-elements","language":["javascript"],"generated":true},"349":{"id":349,"level":1,"title":"intersection-of-two-arrays","language":["javascript"],"generated":true},"350":{"id":350,"level":1,"title":"intersection-of-two-arrays-ii","language":["javascript"],"generated":true},"445":{"id":445,"level":2,"title":"add-two-numbers-ii","language":["javascript"],"generated":true},"447":{"id":447,"level":1,"title":"number-of-boomerangs","language":["javascript"],"generated":true},"454":{"id":454,"level":2,"title":"4sum-ii","language":["javascript"],"generated":true},"476":{"id":476,"level":1,"title":"number-complement","language":["javascript"],"generated":true},"lastUpdatedTime":"2018-04-29","total":738,"solved":57,"locked":133}